{"py/object": "handler.Handler", "players": [{"py/object": "player.player", "games": [{"py/object": "player.player", "games": [{"py/object": "player.player", "games": [{"py/id": 4}], "oponnent_elo": [1200], "elo": 1190.0, "name": "Name", "results": [0], "ID": 1863}, {"py/id": 2}], "oponnent_elo": [1200, 1200], "elo": 1199.71225631668, "name": "Name1", "results": [1, 0], "ID": 5923}, {"py/object": "player.player", "games": [{"py/id": 2}], "oponnent_elo": [1210.28774368332], "elo": 1190.2960185560382, "name": "Name", "results": [0], "ID": 4068}, {"py/object": "player.player", "games": [{"py/id": 2}], "oponnent_elo": [1219.9917251272818], "elo": 1190.5747738950186, "name": "Name", "results": [0], "ID": 1792}], "oponnent_elo": [1210.0, 1200, 1200], "elo": 1229.4169512322633, "name": "Name", "results": [1, 1, 1], "ID": 3945}, {"py/id": 4}, {"py/id": 16}, {"py/id": 12}, {"py/id": 6}]}